seven-segment/v/SevenSegment.v
`default_nettype none

module SevenSegment(input wire CLK,
                    input wire RST,
                    input wire EN,
                    input wire [7:0] DATA,
                    output reg [6:0] SEGMENTS,
                    output reg SEL);

    // Number of clocks between display swap
    parameter THRESHOLD = 100;

    reg [15:0] iCOUNTER;
    initial iCOUNTER = 0;

    // Down Counter 
    always @(posedge CLK)
        if (RST) 
            iCOUNTER <= THRESHOLD;
        else if (EN)
            if (iCOUNTER > 0)
                iCOUNTER <= iCOUNTER - 1;
            else // iCOUNTER == 0
                iCOUNTER <= THRESHOLD;

    // SEL
    always @(posedge CLK)
        if (RST)
            SEL <= 0;
        else if (EN)
            if (iCOUNTER == 0)
                SEL <= ~SEL;

    reg [3:0] iDATA = 0;
    initial iDATA = 0;

    // DATA -> iDATA
    always @(posedge CLK)
        if (RST)
            iDATA <= 0;
        else if (EN)
            if (SEL)
                iDATA <= DATA[7:4];
            else
                iDATA <= DATA[3:0];

    // iDATA -> SEGMENTS
    always @(posedge CLK)
        begin
            if (RST)
                SEGMENTS <= 7'b0000000;
            else if (EN)
                case (iDATA)
                    4'h0: SEGMENTS <= 7'b0111111;
                    4'h1: SEGMENTS <= 7'b0000110;
                    4'h2: SEGMENTS <= 7'b1011011;
                    4'h3: SEGMENTS <= 7'b1001111;
                    4'h4: SEGMENTS <= 7'b1100110;
                    4'h5: SEGMENTS <= 7'b1101101;
                    4'h6: SEGMENTS <= 7'b1011111;
                    4'h7: SEGMENTS <= 7'b0000111;
                    4'h8: SEGMENTS <= 7'b1111111;
                    4'h9: SEGMENTS <= 7'b1111011;
                    4'hA: SEGMENTS <= 7'b1110111;
                    4'hB: SEGMENTS <= 7'b1111100;
                    4'hC: SEGMENTS <= 7'b0111001;
                    4'hD: SEGMENTS <= 7'b1011110;
                    4'hE: SEGMENTS <= 7'b1111001;
                    4'hF: SEGMENTS <= 7'b1110001;
                endcase
        end

endmodule

seven-segment/v/waveform.vcd
$version Generated by VerilatedVcd $end
$timescale 1ps $end
 $scope module TOP $end
  $var wire 1 # CLK $end
  $var wire 1 $ RST $end
  $var wire 1 % EN $end
  $var wire 8 & DATA [7:0] $end
  $var wire 7 ' SEGMENTS [6:0] $end
  $var wire 1 ( SEL $end
  $scope module SevenSegment $end
   $var wire 1 # CLK $end
   $var wire 1 $ RST $end
   $var wire 1 % EN $end
   $var wire 8 & DATA [7:0] $end
   $var wire 7 ' SEGMENTS [6:0] $end
   $var wire 1 ( SEL $end
   $var wire 32 + THRESHOLD [31:0] $end
   $var wire 16 ) iCOUNTER [15:0] $end
   $var wire 4 * iDATA [3:0] $end
  $upscope $end
 $upscope $end
$enddefinitions $end


#8
0#
1$
0%
b00000000 &
b0000000 '
0(
b0000000000000000 )
b0000 *
b00000000000000000000000001100100 +
#10
1#
b0000000001100100 )
#15
0#
#18
#20
1#
#25
0#
#28
0$
1%
#30
1#
b0111111 '
b0000000001100011 )
#35
0#
#38
#40
1#
b0000000001100010 )
#45
0#
#48
#50
1#
b0000000001100001 )
#55
0#
#58
b00000001 &
#60
1#
b0000000001100000 )
b0001 *
#65
0#
#68
#70
1#
b0000110 '
b0000000001011111 )
#75
0#
#78
b00000010 &
#80
1#
b0000000001011110 )
b0010 *
#85
0#
#88
#90
1#
b1011011 '
b0000000001011101 )
#95
0#
#98
b00000011 &
#100
1#
b0000000001011100 )
b0011 *
#105
0#
#108
#110
1#
b1001111 '
b0000000001011011 )
#115
0#
#118
b00000100 &
#120
1#
b0000000001011010 )
b0100 *
#125
0#
#128
#130
1#
b1100110 '
b0000000001011001 )
#135
0#
#138
b00000101 &
#140
1#
b0000000001011000 )
b0101 *
#145
0#
#148
#150
1#
b1101101 '
b0000000001010111 )
#155
0#
#158
b00000110 &
#160
1#
b0000000001010110 )
b0110 *
#165
0#
#168
#170
1#
b1011111 '
b0000000001010101 )
#175
0#
#178
b00000111 &
#180
1#
b0000000001010100 )
b0111 *
#185
0#
#188
#190
1#
b0000111 '
b0000000001010011 )
#195
0#
#198
b00001000 &
#200
1#
b0000000001010010 )
b1000 *
#205
0#
#208
#210
1#
b1111111 '
b0000000001010001 )
#215
0#
#218
b00001001 &
#220
1#
b0000000001010000 )
b1001 *
#225
0#
#228
#230
1#
b1111011 '
b0000000001001111 )
#235
0#
#238
b00001010 &
#240
1#
b0000000001001110 )
b1010 *
#245
0#
#248
#250
1#
b1110111 '
b0000000001001101 )
#255
0#
#258
b00001011 &
#260
1#
b0000000001001100 )
b1011 *
#265
0#
#268
#270
1#
b1111100 '
b0000000001001011 )
#275
0#
#278
b00001100 &
#280
1#
b0000000001001010 )
b1100 *
#285
0#
#288
#290
1#
b0111001 '
b0000000001001001 )
#295
0#
#298
b00001101 &
#300
1#
b0000000001001000 )
b1101 *
#305
0#
#308
#310
1#
b1011110 '
b0000000001000111 )
#315
0#
#318
b00001110 &
#320
1#
b0000000001000110 )
b1110 *
#325
0#
#328
#330
1#
b1111001 '
b0000000001000101 )
#335
0#
#338
b00001111 &
#340
1#
b0000000001000100 )
b1111 *
#345
0#
#348
#350
1#
b1110001 '
b0000000001000011 )
